{
  "git_repository": [
    {
      "id": "coreruleset-v3",
      "name": "Coreruleset v3.3.7",
      "url": "https://github.com/coreruleset/coreruleset.git",
      "commit": "daedded8fe6f132e7db8875f9dd0b02850215b74",
      "post_install": "rm -rf files/coreruleset-v3/tests && cp files/coreruleset-v3/crs-setup.conf.example files/crs-setup-v3.conf"
    },
    {
      "id": "coreruleset-v4",
      "name": "Coreruleset v4.8.0",
      "url": "https://github.com/coreruleset/coreruleset.git",
      "commit": "3dc7e0dbc971a6622ecc273a34c7febc14145b1c",
      "post_install": "rm -rf files/coreruleset-v4/tests && cp files/coreruleset-v4/crs-setup.conf.example files/crs-setup-v4.conf"
    }
  ]
}
